{".class":"MypyFile","_fullname":"spreadsheet_rescue.report","future_import_flags":["annotations"],"is_partial_stub_package":false,"is_stub":false,"names":{".class":"SymbolTable","Alignment":{".class":"SymbolTableNode","kind":"Gdef","node":{".class":"Var","flags":["is_suppressed_import","is_ready","is_inferred"],"fullname":"spreadsheet_rescue.report.Alignment","name":"Alignment","setter_type":null,"type":{".class":"AnyType","missing_import_name":"spreadsheet_rescue.report.Alignment","source_any":null,"type_of_any":3}}},"Any":{".class":"SymbolTableNode","cross_ref":"typing.Any","kind":"Gdef"},"CURRENCY_FMT":{".class":"SymbolTableNode","kind":"Gdef","node":{".class":"Var","flags":["is_ready","is_inferred","has_explicit_value"],"fullname":"spreadsheet_rescue.report.CURRENCY_FMT","name":"CURRENCY_FMT","setter_type":null,"type":"builtins.str"}},"DATE_FMT":{".class":"SymbolTableNode","kind":"Gdef","node":{".class":"Var","flags":["is_ready","is_inferred","has_explicit_value"],"fullname":"spreadsheet_rescue.report.DATE_FMT","name":"DATE_FMT","setter_type":null,"type":"builtins.str"}},"Font":{".class":"SymbolTableNode","kind":"Gdef","node":{".class":"Var","flags":["is_suppressed_import","is_ready","is_inferred"],"fullname":"spreadsheet_rescue.report.Font","name":"Font","setter_type":null,"type":{".class":"AnyType","missing_import_name":"spreadsheet_rescue.report.Font","source_any":null,"type_of_any":3}}},"HEADER_ALIGN":{".class":"SymbolTableNode","kind":"Gdef","node":{".class":"Var","flags":["is_ready","is_inferred","has_explicit_value"],"fullname":"spreadsheet_rescue.report.HEADER_ALIGN","name":"HEADER_ALIGN","setter_type":null,"type":{".class":"AnyType","missing_import_name":"spreadsheet_rescue.report.Alignment","source_any":{".class":"AnyType","missing_import_name":"spreadsheet_rescue.report.Alignment","source_any":null,"type_of_any":3},"type_of_any":7}}},"HEADER_FILL":{".class":"SymbolTableNode","kind":"Gdef","node":{".class":"Var","flags":["is_ready","is_inferred","has_explicit_value"],"fullname":"spreadsheet_rescue.report.HEADER_FILL","name":"HEADER_FILL","setter_type":null,"type":{".class":"AnyType","missing_import_name":"spreadsheet_rescue.report.PatternFill","source_any":{".class":"AnyType","missing_import_name":"spreadsheet_rescue.report.PatternFill","source_any":null,"type_of_any":3},"type_of_any":7}}},"HEADER_FONT":{".class":"SymbolTableNode","kind":"Gdef","node":{".class":"Var","flags":["is_ready","is_inferred","has_explicit_value"],"fullname":"spreadsheet_rescue.report.HEADER_FONT","name":"HEADER_FONT","setter_type":null,"type":{".class":"AnyType","missing_import_name":"spreadsheet_rescue.report.Font","source_any":{".class":"AnyType","missing_import_name":"spreadsheet_rescue.report.Font","source_any":null,"type_of_any":3},"type_of_any":7}}},"INT_FMT":{".class":"SymbolTableNode","kind":"Gdef","node":{".class":"Var","flags":["is_ready","is_inferred","has_explicit_value"],"fullname":"spreadsheet_rescue.report.INT_FMT","name":"INT_FMT","setter_type":null,"type":"builtins.str"}},"Iterable":{".class":"SymbolTableNode","cross_ref":"typing.Iterable","kind":"Gdef"},"KPI_FILL":{".class":"SymbolTableNode","kind":"Gdef","node":{".class":"Var","flags":["is_ready","is_inferred","has_explicit_value"],"fullname":"spreadsheet_rescue.report.KPI_FILL","name":"KPI_FILL","setter_type":null,"type":{".class":"AnyType","missing_import_name":"spreadsheet_rescue.report.PatternFill","source_any":{".class":"AnyType","missing_import_name":"spreadsheet_rescue.report.PatternFill","source_any":null,"type_of_any":3},"type_of_any":7}}},"LABEL_FONT":{".class":"SymbolTableNode","kind":"Gdef","node":{".class":"Var","flags":["is_ready","is_inferred","has_explicit_value"],"fullname":"spreadsheet_rescue.report.LABEL_FONT","name":"LABEL_FONT","setter_type":null,"type":{".class":"AnyType","missing_import_name":"spreadsheet_rescue.report.Font","source_any":{".class":"AnyType","missing_import_name":"spreadsheet_rescue.report.Font","source_any":null,"type_of_any":3},"type_of_any":7}}},"NOTE_FILL":{".class":"SymbolTableNode","kind":"Gdef","node":{".class":"Var","flags":["is_ready","is_inferred","has_explicit_value"],"fullname":"spreadsheet_rescue.report.NOTE_FILL","name":"NOTE_FILL","setter_type":null,"type":{".class":"AnyType","missing_import_name":"spreadsheet_rescue.report.PatternFill","source_any":{".class":"AnyType","missing_import_name":"spreadsheet_rescue.report.PatternFill","source_any":null,"type_of_any":3},"type_of_any":7}}},"PCT_FMT":{".class":"SymbolTableNode","kind":"Gdef","node":{".class":"Var","flags":["is_ready","is_inferred","has_explicit_value"],"fullname":"spreadsheet_rescue.report.PCT_FMT","name":"PCT_FMT","setter_type":null,"type":"builtins.str"}},"Path":{".class":"SymbolTableNode","cross_ref":"pathlib.Path","kind":"Gdef"},"PatternFill":{".class":"SymbolTableNode","kind":"Gdef","node":{".class":"Var","flags":["is_suppressed_import","is_ready","is_inferred"],"fullname":"spreadsheet_rescue.report.PatternFill","name":"PatternFill","setter_type":null,"type":{".class":"AnyType","missing_import_name":"spreadsheet_rescue.report.PatternFill","source_any":null,"type_of_any":3}}},"QCReport":{".class":"SymbolTableNode","cross_ref":"spreadsheet_rescue.models.QCReport","kind":"Gdef"},"SUBTITLE_FONT":{".class":"SymbolTableNode","kind":"Gdef","node":{".class":"Var","flags":["is_ready","is_inferred","has_explicit_value"],"fullname":"spreadsheet_rescue.report.SUBTITLE_FONT","name":"SUBTITLE_FONT","setter_type":null,"type":{".class":"AnyType","missing_import_name":"spreadsheet_rescue.report.Font","source_any":{".class":"AnyType","missing_import_name":"spreadsheet_rescue.report.Font","source_any":null,"type_of_any":3},"type_of_any":7}}},"TITLE_FONT":{".class":"SymbolTableNode","kind":"Gdef","node":{".class":"Var","flags":["is_ready","is_inferred","has_explicit_value"],"fullname":"spreadsheet_rescue.report.TITLE_FONT","name":"TITLE_FONT","setter_type":null,"type":{".class":"AnyType","missing_import_name":"spreadsheet_rescue.report.Font","source_any":{".class":"AnyType","missing_import_name":"spreadsheet_rescue.report.Font","source_any":null,"type_of_any":3},"type_of_any":7}}},"Table":{".class":"SymbolTableNode","kind":"Gdef","node":{".class":"Var","flags":["is_suppressed_import","is_ready","is_inferred"],"fullname":"spreadsheet_rescue.report.Table","name":"Table","setter_type":null,"type":{".class":"AnyType","missing_import_name":"spreadsheet_rescue.report.Table","source_any":null,"type_of_any":3}}},"TableStyleInfo":{".class":"SymbolTableNode","kind":"Gdef","node":{".class":"Var","flags":["is_suppressed_import","is_ready","is_inferred"],"fullname":"spreadsheet_rescue.report.TableStyleInfo","name":"TableStyleInfo","setter_type":null,"type":{".class":"AnyType","missing_import_name":"spreadsheet_rescue.report.TableStyleInfo","source_any":null,"type_of_any":3}}},"VALUE_FONT":{".class":"SymbolTableNode","kind":"Gdef","node":{".class":"Var","flags":["is_ready","is_inferred","has_explicit_value"],"fullname":"spreadsheet_rescue.report.VALUE_FONT","name":"VALUE_FONT","setter_type":null,"type":{".class":"AnyType","missing_import_name":"spreadsheet_rescue.report.Font","source_any":{".class":"AnyType","missing_import_name":"spreadsheet_rescue.report.Font","source_any":null,"type_of_any":3},"type_of_any":7}}},"WARN_FONT":{".class":"SymbolTableNode","kind":"Gdef","node":{".class":"Var","flags":["is_ready","is_inferred","has_explicit_value"],"fullname":"spreadsheet_rescue.report.WARN_FONT","name":"WARN_FONT","setter_type":null,"type":{".class":"AnyType","missing_import_name":"spreadsheet_rescue.report.Font","source_any":{".class":"AnyType","missing_import_name":"spreadsheet_rescue.report.Font","source_any":null,"type_of_any":3},"type_of_any":7}}},"Workbook":{".class":"SymbolTableNode","kind":"Gdef","node":{".class":"Var","flags":["is_suppressed_import","is_ready","is_inferred"],"fullname":"spreadsheet_rescue.report.Workbook","name":"Workbook","setter_type":null,"type":{".class":"AnyType","missing_import_name":"spreadsheet_rescue.report.Workbook","source_any":null,"type_of_any":3}}},"Worksheet":{".class":"SymbolTableNode","kind":"Gdef","node":{".class":"Var","flags":["is_suppressed_import","is_ready","is_inferred"],"fullname":"spreadsheet_rescue.report.Worksheet","name":"Worksheet","setter_type":null,"type":{".class":"AnyType","missing_import_name":"spreadsheet_rescue.report.Worksheet","source_any":null,"type_of_any":3}}},"_AUTO_WIDTH_SAMPLE_ROWS":{".class":"SymbolTableNode","kind":"Gdef","node":{".class":"Var","flags":["is_ready","is_inferred","has_explicit_value"],"fullname":"spreadsheet_rescue.report._AUTO_WIDTH_SAMPLE_ROWS","name":"_AUTO_WIDTH_SAMPLE_ROWS","setter_type":null,"type":"builtins.int"}},"_COL_FORMATS":{".class":"SymbolTableNode","kind":"Gdef","node":{".class":"Var","flags":["is_ready","has_explicit_value"],"fullname":"spreadsheet_rescue.report._COL_FORMATS","name":"_COL_FORMATS","setter_type":null,"type":{".class":"Instance","args":["builtins.str","builtins.str"],"extra_attrs":null,"type_ref":"builtins.dict"}}},"__annotations__":{".class":"SymbolTableNode","kind":"Gdef","node":{".class":"Var","flags":["is_ready"],"fullname":"spreadsheet_rescue.report.__annotations__","name":"__annotations__","setter_type":null,"type":{".class":"Instance","args":["builtins.str",{".class":"AnyType","missing_import_name":null,"source_any":null,"type_of_any":6}],"extra_attrs":null,"type_ref":"builtins.dict"}}},"__doc__":{".class":"SymbolTableNode","kind":"Gdef","node":{".class":"Var","flags":["is_ready"],"fullname":"spreadsheet_rescue.report.__doc__","name":"__doc__","setter_type":null,"type":"builtins.str"}},"__file__":{".class":"SymbolTableNode","kind":"Gdef","node":{".class":"Var","flags":["is_ready"],"fullname":"spreadsheet_rescue.report.__file__","name":"__file__","setter_type":null,"type":"builtins.str"}},"__name__":{".class":"SymbolTableNode","kind":"Gdef","node":{".class":"Var","flags":["is_ready"],"fullname":"spreadsheet_rescue.report.__name__","name":"__name__","setter_type":null,"type":"builtins.str"}},"__package__":{".class":"SymbolTableNode","kind":"Gdef","node":{".class":"Var","flags":["is_ready"],"fullname":"spreadsheet_rescue.report.__package__","name":"__package__","setter_type":null,"type":"builtins.str"}},"__spec__":{".class":"SymbolTableNode","kind":"Gdef","node":{".class":"Var","flags":["is_ready"],"fullname":"spreadsheet_rescue.report.__spec__","name":"__spec__","setter_type":null,"type":"_frozen_importlib.ModuleSpec"}},"_add_excel_table":{".class":"SymbolTableNode","kind":"Gdef","node":{".class":"FuncDef","abstract_status":0,"arg_kinds":[0,0,0,0],"arg_names":["ws","name","ncols","nrows"],"dataclass_transform_spec":null,"deprecated":null,"flags":[],"fullname":"spreadsheet_rescue.report._add_excel_table","name":"_add_excel_table","original_first_arg":"ws","type":{".class":"CallableType","arg_kinds":[0,0,0,0],"arg_names":["ws","name","ncols","nrows"],"arg_types":[{".class":"AnyType","missing_import_name":"spreadsheet_rescue.report.Worksheet","source_any":null,"type_of_any":3},"builtins.str","builtins.int","builtins.int"],"fallback":"builtins.function","from_concatenate":false,"implicit":false,"imprecise_arg_kinds":false,"is_bound":false,"is_ellipsis_args":false,"name":"_add_excel_table","ret_type":{".class":"NoneType"},"type_guard":null,"type_is":null,"unpack_kwargs":false,"variables":[]}}},"_apply_number_formats":{".class":"SymbolTableNode","kind":"Gdef","node":{".class":"FuncDef","abstract_status":0,"arg_kinds":[0,0],"arg_names":["ws","col_names"],"dataclass_transform_spec":null,"deprecated":null,"flags":[],"fullname":"spreadsheet_rescue.report._apply_number_formats","name":"_apply_number_formats","original_first_arg":"ws","type":{".class":"CallableType","arg_kinds":[0,0],"arg_names":["ws","col_names"],"arg_types":[{".class":"AnyType","missing_import_name":"spreadsheet_rescue.report.Worksheet","source_any":null,"type_of_any":3},{".class":"Instance","args":["builtins.str"],"extra_attrs":null,"type_ref":"builtins.list"}],"fallback":"builtins.function","from_concatenate":false,"implicit":false,"imprecise_arg_kinds":false,"is_bound":false,"is_ellipsis_args":false,"name":"_apply_number_formats","ret_type":{".class":"NoneType"},"type_guard":null,"type_is":null,"unpack_kwargs":false,"variables":[]}}},"_auto_width":{".class":"SymbolTableNode","kind":"Gdef","node":{".class":"FuncDef","abstract_status":0,"arg_kinds":[0],"arg_names":["ws"],"dataclass_transform_spec":null,"deprecated":null,"flags":[],"fullname":"spreadsheet_rescue.report._auto_width","name":"_auto_width","original_first_arg":"ws","type":{".class":"CallableType","arg_kinds":[0],"arg_names":["ws"],"arg_types":[{".class":"AnyType","missing_import_name":"spreadsheet_rescue.report.Worksheet","source_any":null,"type_of_any":3}],"fallback":"builtins.function","from_concatenate":false,"implicit":false,"imprecise_arg_kinds":false,"is_bound":false,"is_ellipsis_args":false,"name":"_auto_width","ret_type":{".class":"NoneType"},"type_guard":null,"type_is":null,"unpack_kwargs":false,"variables":[]}}},"_df_to_sheet":{".class":"SymbolTableNode","kind":"Gdef","node":{".class":"FuncDef","abstract_status":0,"arg_kinds":[0,0,0,5],"arg_names":["wb","name","df","as_table"],"dataclass_transform_spec":null,"deprecated":null,"flags":[],"fullname":"spreadsheet_rescue.report._df_to_sheet","name":"_df_to_sheet","original_first_arg":"wb","type":{".class":"CallableType","arg_kinds":[0,0,0,5],"arg_names":["wb","name","df","as_table"],"arg_types":[{".class":"AnyType","missing_import_name":"spreadsheet_rescue.report.Workbook","source_any":null,"type_of_any":3},"builtins.str","pandas.core.frame.DataFrame","builtins.bool"],"fallback":"builtins.function","from_concatenate":false,"implicit":false,"imprecise_arg_kinds":false,"is_bound":false,"is_ellipsis_args":false,"name":"_df_to_sheet","ret_type":{".class":"NoneType"},"type_guard":null,"type_is":null,"unpack_kwargs":false,"variables":[]}}},"_excel_value":{".class":"SymbolTableNode","kind":"Gdef","node":{".class":"FuncDef","abstract_status":0,"arg_kinds":[0],"arg_names":["val"],"dataclass_transform_spec":null,"deprecated":null,"flags":[],"fullname":"spreadsheet_rescue.report._excel_value","name":"_excel_value","original_first_arg":"val","type":{".class":"CallableType","arg_kinds":[0],"arg_names":["val"],"arg_types":[{".class":"AnyType","missing_import_name":null,"source_any":null,"type_of_any":2}],"fallback":"builtins.function","from_concatenate":false,"implicit":false,"imprecise_arg_kinds":false,"is_bound":false,"is_ellipsis_args":false,"name":"_excel_value","ret_type":{".class":"AnyType","missing_import_name":null,"source_any":null,"type_of_any":2},"type_guard":null,"type_is":null,"unpack_kwargs":false,"variables":[]}}},"_sanitize_table_name":{".class":"SymbolTableNode","kind":"Gdef","node":{".class":"FuncDef","abstract_status":0,"arg_kinds":[0],"arg_names":["name"],"dataclass_transform_spec":null,"deprecated":null,"flags":[],"fullname":"spreadsheet_rescue.report._sanitize_table_name","name":"_sanitize_table_name","original_first_arg":"name","type":{".class":"CallableType","arg_kinds":[0],"arg_names":["name"],"arg_types":["builtins.str"],"fallback":"builtins.function","from_concatenate":false,"implicit":false,"imprecise_arg_kinds":false,"is_bound":false,"is_ellipsis_args":false,"name":"_sanitize_table_name","ret_type":"builtins.str","type_guard":null,"type_is":null,"unpack_kwargs":false,"variables":[]}}},"_style_header":{".class":"SymbolTableNode","kind":"Gdef","node":{".class":"FuncDef","abstract_status":0,"arg_kinds":[0,0],"arg_names":["ws","ncols"],"dataclass_transform_spec":null,"deprecated":null,"flags":[],"fullname":"spreadsheet_rescue.report._style_header","name":"_style_header","original_first_arg":"ws","type":{".class":"CallableType","arg_kinds":[0,0],"arg_names":["ws","ncols"],"arg_types":[{".class":"AnyType","missing_import_name":"spreadsheet_rescue.report.Worksheet","source_any":null,"type_of_any":3},"builtins.int"],"fallback":"builtins.function","from_concatenate":false,"implicit":false,"imprecise_arg_kinds":false,"is_bound":false,"is_ellipsis_args":false,"name":"_style_header","ret_type":{".class":"NoneType"},"type_guard":null,"type_is":null,"unpack_kwargs":false,"variables":[]}}},"_unique_table_name":{".class":"SymbolTableNode","kind":"Gdef","node":{".class":"FuncDef","abstract_status":0,"arg_kinds":[0,0],"arg_names":["ws","base_name"],"dataclass_transform_spec":null,"deprecated":null,"flags":[],"fullname":"spreadsheet_rescue.report._unique_table_name","name":"_unique_table_name","original_first_arg":"ws","type":{".class":"CallableType","arg_kinds":[0,0],"arg_names":["ws","base_name"],"arg_types":[{".class":"AnyType","missing_import_name":"spreadsheet_rescue.report.Worksheet","source_any":null,"type_of_any":3},"builtins.str"],"fallback":"builtins.function","from_concatenate":false,"implicit":false,"imprecise_arg_kinds":false,"is_bound":false,"is_ellipsis_args":false,"name":"_unique_table_name","ret_type":"builtins.str","type_guard":null,"type_is":null,"unpack_kwargs":false,"variables":[]}}},"_write_dashboard":{".class":"SymbolTableNode","kind":"Gdef","node":{".class":"FuncDef","abstract_status":0,"arg_kinds":[0,0,0],"arg_names":["wb","kpis","qc"],"dataclass_transform_spec":null,"deprecated":null,"flags":[],"fullname":"spreadsheet_rescue.report._write_dashboard","name":"_write_dashboard","original_first_arg":"wb","type":{".class":"CallableType","arg_kinds":[0,0,0],"arg_names":["wb","kpis","qc"],"arg_types":[{".class":"AnyType","missing_import_name":"spreadsheet_rescue.report.Workbook","source_any":null,"type_of_any":3},{".class":"Instance","args":["builtins.str",{".class":"AnyType","missing_import_name":null,"source_any":null,"type_of_any":2}],"extra_attrs":null,"type_ref":"builtins.dict"},"spreadsheet_rescue.models.QCReport"],"fallback":"builtins.function","from_concatenate":false,"implicit":false,"imprecise_arg_kinds":false,"is_bound":false,"is_ellipsis_args":false,"name":"_write_dashboard","ret_type":{".class":"NoneType"},"type_guard":null,"type_is":null,"unpack_kwargs":false,"variables":[]}}},"annotations":{".class":"SymbolTableNode","cross_ref":"__future__.annotations","kind":"Gdef"},"cast":{".class":"SymbolTableNode","cross_ref":"typing.cast","kind":"Gdef"},"datetime":{".class":"SymbolTableNode","cross_ref":"datetime.datetime","kind":"Gdef"},"get_column_letter":{".class":"SymbolTableNode","kind":"Gdef","node":{".class":"Var","flags":["is_suppressed_import","is_ready","is_inferred"],"fullname":"spreadsheet_rescue.report.get_column_letter","name":"get_column_letter","setter_type":null,"type":{".class":"AnyType","missing_import_name":"spreadsheet_rescue.report.get_column_letter","source_any":null,"type_of_any":3}}},"pd":{".class":"SymbolTableNode","cross_ref":"pandas","kind":"Gdef"},"re":{".class":"SymbolTableNode","cross_ref":"re","kind":"Gdef"},"timezone":{".class":"SymbolTableNode","cross_ref":"datetime.timezone","kind":"Gdef"},"write_report":{".class":"SymbolTableNode","kind":"Gdef","node":{".class":"FuncDef","abstract_status":0,"arg_kinds":[0,0,0,0,0,0,1],"arg_names":["out_dir","clean_df","kpis","weekly","top_products","top_regions","qc"],"dataclass_transform_spec":null,"deprecated":null,"flags":[],"fullname":"spreadsheet_rescue.report.write_report","name":"write_report","original_first_arg":"out_dir","type":{".class":"CallableType","arg_kinds":[0,0,0,0,0,0,1],"arg_names":["out_dir","clean_df","kpis","weekly","top_products","top_regions","qc"],"arg_types":["pathlib.Path","pandas.core.frame.DataFrame",{".class":"Instance","args":["builtins.str",{".class":"AnyType","missing_import_name":null,"source_any":null,"type_of_any":2}],"extra_attrs":null,"type_ref":"builtins.dict"},"pandas.core.frame.DataFrame","pandas.core.frame.DataFrame","pandas.core.frame.DataFrame",{".class":"UnionType","items":["spreadsheet_rescue.models.QCReport",{".class":"NoneType"}],"uses_pep604_syntax":true}],"fallback":"builtins.function","from_concatenate":false,"implicit":false,"imprecise_arg_kinds":false,"is_bound":false,"is_ellipsis_args":false,"name":"write_report","ret_type":"pathlib.Path","type_guard":null,"type_is":null,"unpack_kwargs":false,"variables":[]}}}},"path":"src/spreadsheet_rescue/report.py"}